{
  "editor": {
    "title": "Resume Builder",
    "subtitle": "Fill the form on the left and see live preview on the right."
  },
  "basic": {
    "sectionTitle": "Basic information",
    "sectionSubtitle": "This information will appear in the header of your resume.",
    "fullName": "Full name",
    "position": "Desired position"
  },
  "landing": {
    "hero": {
      "trustSignal": "Free · No signup · No card",
      "headline": "Resumes that {highlight} — without extra steps.",
      "headlineHighlight": "pass ATS",
      "subheadline": "Fill in your details, choose a template, and get a resume ready to apply.",
      "ctaPrimary": "Build resume",
      "ctaSecondary": "View templates",
      "features": {
        "atsOptimized": "ATS-ready",
        "instantExport": "Instant PDF export",
        "noSignup": "No signup required"
      }
    }
  }
}
